big_o/__init__.py
big_o/big_o.py
big_o/complexities.py
big_o/datagen.py
big_o/reports.py
big_o/test/__init__.py
big_o/test/test_big_o.py
big_o/test/test_complexities.py
big_o/test/test_complexityclass_comparisons.py
big_o/test/test_datagen.py
big_o/test/test_reports.py
big_O_latest-0.10.3.dist-info/LICENSE.txt
big_O_latest-0.10.3.dist-info/METADATA
big_O_latest-0.10.3.dist-info/WHEEL
big_O_latest-0.10.3.dist-info/top_level.txt
big_O_latest-0.10.3.dist-info/RECORD
