Metadata-Version: 2.1
Name: big-O-latest
Version: 0.10.3
Summary: Empirical estimation of time complexity from execution time, more recent version
Home-page: https://github.com/DanielHabenicht/big_O
Author: Pietro Berkes
Author-email: pietro.berkes@googlemail.com
License: LICENSE.txt
License-File: LICENSE.txt
Requires-Dist: numpy
